okwugbe/__init__.py
okwugbe/commonvoice.py
okwugbe/decoder.py
okwugbe/earlystopping.py
okwugbe/metrics.py
okwugbe/model.py
okwugbe/okwugbe_asr.py
okwugbe/process.py
okwugbe/texttransform.py
okwugbe/train_eval.py
okwugbe-0.1.8.dist-info/LICENSE
okwugbe-0.1.8.dist-info/METADATA
okwugbe-0.1.8.dist-info/WHEEL
okwugbe-0.1.8.dist-info/top_level.txt
okwugbe-0.1.8.dist-info/RECORD
