Metadata-Version: 2.1
Name: okwugbe
Version: 0.1.8
Summary: Automatic Speech Recognition Library for African Languages
Home-page: https://github.com/edaiofficial/asr-africa
Author: Bonaventure F. P. Dossou - Chris C. Emezue
Author-email: edai.official.edai@gmail.com
License: UNKNOWN
Project-URL: Bug Tracker, https://github.com/edaiofficial/asr-africa/issues
Platform: UNKNOWN
Classifier: Programming Language :: Python :: 3
Classifier: License :: OSI Approved :: MIT License
Classifier: Operating System :: OS Independent
Requires-Python: >=3.6
License-File: LICENSE
Requires-Dist: setuptools (>=42)
Requires-Dist: wheel
Requires-Dist: numpy
Requires-Dist: torch
Requires-Dist: torchaudio
Requires-Dist: datasets (==1.12.1)
Requires-Dist: colorama
Requires-Dist: ipython (==5.5.0)
Requires-Dist: livelossplot
Requires-Dist: commonvoice-utils
